{
    "id": "e52d60d5d3d8396036e71313f2d96d9e",
    "name": "Barcode",
    "description": "Autogeneration of Barcode Schema.org object.",
    "auth": null,
    "events": null,
    "variables": [],
    "order": [],
    "folders_order": [],
    "folders": [],
    "requests": [
        {
            "id": "11574f3f8e190694b01a7e986fe712c9",
            "name": "\/Barcode\/",
            "url": "{{url}}\/Barcode\/",
            "description": "Autogeneration of Barcode Schema.org object.",
            "data": [],
            "dataMode": "raw",
            "headerData": null,
            "method": "GET",
            "pathVariableData": null,
            "queryParams": null,
            "auth": null,
            "events": null,
            "folder": null,
            "protocolProfileBehavior": {
                "disableBodyPruning": true
            },
            "responses": [
                {
                    "id": "11574f3f8e190694b01a7e986fe712c9",
                    "name": "Default",
                    "status": "200",
                    "mime": null,
                    "language": null,
                    "text": "\"{\n    \"exifData\": \"String Content\",\n    \"representativeOfPage\": 1,\n    \"thumbnail\": {},\n    \"caption\": \"String Content\",\n    \"uploadDate\": \"String Content\",\n    \"playerType\": \"String Content\",\n    \"height\": {},\n    \"bitrate\": \"String Content\",\n    \"requiresSubscription\": 1,\n    \"regionsAllowed\": {},\n    \"contentSize\": \"String Content\",\n    \"embedUrl\": {},\n    \"width\": {},\n    \"contentUrl\": {},\n    \"associatedArticle\": {},\n    \"productionCompany\": {},\n    \"duration\": {},\n    \"encodesCreativeWork\": {},\n    \"encodingFormat\": \"String Content\"\n}\"",
                    "responseCode": {
                        "code": 200,
                        "name": ""
                    },
                    "requestObject": {
                        "url": "{{url}}\/Barcode\/",
                        "method": "GET",
                        "data": "",
                        "dataMode": "raw",
                        "protocolProfileBehavior": []
                    },
                    "headers": null,
                    "cookies": null,
                    "request": "0090271e4b00e7a63d68d217703c2af5",
                    "collection": "e52d60d5d3d8396036e71313f2d96d9e"
                }
            ],
            "currentHelper": null,
            "helperAttributes": null,
            "collectionId": "e52d60d5d3d8396036e71313f2d96d9e",
            "rawModeData": ""
        }
    ]
}