{
    "id": "1732f8ecc413a2db38ccc73f16ad0daa",
    "name": "Bed Details",
    "description": "Autogeneration of Bed Details Schema.org object.",
    "auth": null,
    "events": null,
    "variables": [],
    "order": [],
    "folders_order": [],
    "folders": [],
    "requests": [
        {
            "id": "ce0d420028db533ba5cb18bf86237a1f",
            "name": "\/Bed-Details\/",
            "url": "{{url}}\/Bed-Details\/",
            "description": "Autogeneration of Bed Details Schema.org object.",
            "data": [],
            "dataMode": "raw",
            "headerData": null,
            "method": "GET",
            "pathVariableData": null,
            "queryParams": null,
            "auth": null,
            "events": null,
            "folder": null,
            "protocolProfileBehavior": {
                "disableBodyPruning": true
            },
            "responses": [
                {
                    "id": "ce0d420028db533ba5cb18bf86237a1f",
                    "name": "Default",
                    "status": "200",
                    "mime": null,
                    "language": null,
                    "text": "\"{\n    \"typeOfBed\": \"String Content\",\n    \"numberOfBeds\": 10,\n    \"sameAs\": {},\n    \"url\": {},\n    \"image\": {},\n    \"additionalType\": {},\n    \"name\": \"String Content\",\n    \"identifier\": {},\n    \"potentialAction\": {},\n    \"mainEntityOfPage\": {},\n    \"description\": \"String Content\",\n    \"disambiguatingDescription\": \"String Content\",\n    \"alternateName\": \"String Content\"\n}\"",
                    "responseCode": {
                        "code": 200,
                        "name": ""
                    },
                    "requestObject": {
                        "url": "{{url}}\/Bed-Details\/",
                        "method": "GET",
                        "data": "",
                        "dataMode": "raw",
                        "protocolProfileBehavior": []
                    },
                    "headers": null,
                    "cookies": null,
                    "request": "9e297945e32d1491459dc717ea50171c",
                    "collection": "1732f8ecc413a2db38ccc73f16ad0daa"
                }
            ],
            "currentHelper": null,
            "helperAttributes": null,
            "collectionId": "1732f8ecc413a2db38ccc73f16ad0daa",
            "rawModeData": ""
        }
    ]
}