{
    "id": "45eff37e4c3ace78e4af8c8c810fbe79",
    "name": "Bus Trip",
    "description": "Autogeneration of Bus Trip Schema.org object.",
    "auth": null,
    "events": null,
    "variables": [],
    "order": [],
    "folders_order": [],
    "folders": [],
    "requests": [
        {
            "id": "6b0b4e546fc12f6901427a6c484d26d4",
            "name": "\/Bus-Trip\/",
            "url": "{{url}}\/Bus-Trip\/",
            "description": "Autogeneration of Bus Trip Schema.org object.",
            "data": [],
            "dataMode": "raw",
            "headerData": null,
            "method": "GET",
            "pathVariableData": null,
            "queryParams": null,
            "auth": null,
            "events": null,
            "folder": null,
            "protocolProfileBehavior": {
                "disableBodyPruning": true
            },
            "responses": [
                {
                    "id": "6b0b4e546fc12f6901427a6c484d26d4",
                    "name": "Default",
                    "status": "200",
                    "mime": null,
                    "language": null,
                    "text": "{\n    \"provider\": {},\n    \"busName\": \"String Content\",\n    \"departureBusStop\": {},\n    \"arrivalBusStop\": {},\n    \"arrivalTime\": \"String Content\",\n    \"busNumber\": \"String Content\",\n    \"departureTime\": \"String Content\"\n}",
                    "responseCode": {
                        "code": 200,
                        "name": ""
                    },
                    "requestObject": {
                        "url": "{{url}}\/Bus-Trip\/",
                        "method": "GET",
                        "data": "",
                        "dataMode": "raw",
                        "protocolProfileBehavior": []
                    },
                    "headers": null,
                    "cookies": null,
                    "request": "4e8b8ba957270eaf4ca760a08fad072f",
                    "collection": "45eff37e4c3ace78e4af8c8c810fbe79"
                }
            ],
            "currentHelper": null,
            "helperAttributes": null,
            "collectionId": "45eff37e4c3ace78e4af8c8c810fbe79",
            "rawModeData": ""
        }
    ]
}