{
    "id": "3f1bf6b8ba54862037bc189757ef18e4",
    "name": "Computer Store",
    "description": "Autogeneration of Computer Store Schema.org object.",
    "auth": null,
    "events": null,
    "variables": [],
    "order": [],
    "folders_order": [],
    "folders": [],
    "requests": [
        {
            "id": "7019b3a27dedd95ed1cdc608fe50931f",
            "name": "\/Computer-Store\/",
            "url": "{{url}}\/Computer-Store\/",
            "description": "Autogeneration of Computer Store Schema.org object.",
            "data": [],
            "dataMode": "raw",
            "headerData": null,
            "method": "GET",
            "pathVariableData": null,
            "queryParams": null,
            "auth": null,
            "events": null,
            "folder": null,
            "protocolProfileBehavior": {
                "disableBodyPruning": true
            },
            "responses": [
                {
                    "id": "7019b3a27dedd95ed1cdc608fe50931f",
                    "name": "Default",
                    "status": "200",
                    "mime": null,
                    "language": null,
                    "text": "\"[]\"",
                    "responseCode": {
                        "code": 200,
                        "name": ""
                    },
                    "requestObject": {
                        "url": "{{url}}\/Computer-Store\/",
                        "method": "GET",
                        "data": "",
                        "dataMode": "raw",
                        "protocolProfileBehavior": []
                    },
                    "headers": null,
                    "cookies": null,
                    "request": "22edfc8741edf09505351878e7edef94",
                    "collection": "3f1bf6b8ba54862037bc189757ef18e4"
                }
            ],
            "currentHelper": null,
            "helperAttributes": null,
            "collectionId": "3f1bf6b8ba54862037bc189757ef18e4",
            "rawModeData": ""
        }
    ]
}