{
    "id": "45919a140c65aaabc69ab3df738895cc",
    "name": "Government Building",
    "description": "Autogeneration of Government Building Schema.org object.",
    "auth": null,
    "events": null,
    "variables": [],
    "order": [],
    "folders_order": [],
    "folders": [],
    "requests": [
        {
            "id": "8bc677be8beec0566a787f87763d7190",
            "name": "\/government-building\/",
            "url": "{{url}}\/government-building\/",
            "description": "Autogeneration of Government Building Schema.org object.",
            "data": [],
            "dataMode": "raw",
            "headerData": null,
            "method": "GET",
            "pathVariableData": null,
            "queryParams": null,
            "auth": null,
            "events": null,
            "folder": null,
            "protocolProfileBehavior": {
                "disableBodyPruning": true
            },
            "responses": [
                {
                    "id": "8bc677be8beec0566a787f87763d7190",
                    "name": "Default",
                    "status": "200",
                    "mime": null,
                    "language": null,
                    "text": "{\n    \"openingHours\": \"String Content\"\n}",
                    "responseCode": {
                        "code": 200,
                        "name": ""
                    },
                    "requestObject": {
                        "url": "{{url}}\/government-building\/",
                        "method": "GET",
                        "data": "",
                        "dataMode": "raw",
                        "protocolProfileBehavior": []
                    },
                    "headers": null,
                    "cookies": null,
                    "request": "6c1ef127f7235a624052662233d0e8f0",
                    "collection": "45919a140c65aaabc69ab3df738895cc"
                }
            ],
            "currentHelper": null,
            "helperAttributes": null,
            "collectionId": "45919a140c65aaabc69ab3df738895cc",
            "rawModeData": ""
        }
    ]
}