{
    "id": "ea3e16f13091cf1a691ba517bfc646f6",
    "name": "Health Club",
    "description": "Autogeneration of Health Club Schema.org object.",
    "auth": null,
    "events": null,
    "variables": [],
    "order": [],
    "folders_order": [],
    "folders": [],
    "requests": [
        {
            "id": "d64827decc5d52a909266843972e781a",
            "name": "\/Health-Club\/",
            "url": "{{url}}\/Health-Club\/",
            "description": "Autogeneration of Health Club Schema.org object.",
            "data": [],
            "dataMode": "raw",
            "headerData": null,
            "method": "GET",
            "pathVariableData": null,
            "queryParams": null,
            "auth": null,
            "events": null,
            "folder": null,
            "protocolProfileBehavior": {
                "disableBodyPruning": true
            },
            "responses": [
                {
                    "id": "d64827decc5d52a909266843972e781a",
                    "name": "Default",
                    "status": "200",
                    "mime": null,
                    "language": null,
                    "text": "[]",
                    "responseCode": {
                        "code": 200,
                        "name": ""
                    },
                    "requestObject": {
                        "url": "{{url}}\/Health-Club\/",
                        "method": "GET",
                        "data": "",
                        "dataMode": "raw",
                        "protocolProfileBehavior": []
                    },
                    "headers": null,
                    "cookies": null,
                    "request": "3746b2de1b394f4cc4292267eb8442a4",
                    "collection": "ea3e16f13091cf1a691ba517bfc646f6"
                }
            ],
            "currentHelper": null,
            "helperAttributes": null,
            "collectionId": "ea3e16f13091cf1a691ba517bfc646f6",
            "rawModeData": ""
        }
    ]
}