{
    "id": "da095023eec14e15e3d48b01366e388c",
    "name": "Locker Delivery",
    "description": "Autogeneration of Locker Delivery Schema.org object.",
    "auth": null,
    "events": null,
    "variables": [],
    "order": [],
    "folders_order": [],
    "folders": [],
    "requests": [
        {
            "id": "ea5299264f58b3ef48fb1fc1c63a7172",
            "name": "\/Locker-Delivery\/",
            "url": "{{url}}\/Locker-Delivery\/",
            "description": "Autogeneration of Locker Delivery Schema.org object.",
            "data": [],
            "dataMode": "raw",
            "headerData": null,
            "method": "GET",
            "pathVariableData": null,
            "queryParams": null,
            "auth": null,
            "events": null,
            "folder": null,
            "protocolProfileBehavior": {
                "disableBodyPruning": true
            },
            "responses": [
                {
                    "id": "ea5299264f58b3ef48fb1fc1c63a7172",
                    "name": "Default",
                    "status": "200",
                    "mime": null,
                    "language": null,
                    "text": "[]",
                    "responseCode": {
                        "code": 200,
                        "name": ""
                    },
                    "requestObject": {
                        "url": "{{url}}\/Locker-Delivery\/",
                        "method": "GET",
                        "data": "",
                        "dataMode": "raw",
                        "protocolProfileBehavior": []
                    },
                    "headers": null,
                    "cookies": null,
                    "request": "f47a666ee17c73226b7d69b165c856ea",
                    "collection": "da095023eec14e15e3d48b01366e388c"
                }
            ],
            "currentHelper": null,
            "helperAttributes": null,
            "collectionId": "da095023eec14e15e3d48b01366e388c",
            "rawModeData": ""
        }
    ]
}