{
    "id": "a014bbfde60448503226075a3dab6b08",
    "name": "Moving Company",
    "description": "Autogeneration of Moving Company Schema.org object.",
    "auth": null,
    "events": null,
    "variables": [],
    "order": [],
    "folders_order": [],
    "folders": [],
    "requests": [
        {
            "id": "6aa33c342b5ec0dd66fd130d96c95bee",
            "name": "\/Moving-Company\/",
            "url": "{{url}}\/Moving-Company\/",
            "description": "Autogeneration of Moving Company Schema.org object.",
            "data": [],
            "dataMode": "raw",
            "headerData": null,
            "method": "GET",
            "pathVariableData": null,
            "queryParams": null,
            "auth": null,
            "events": null,
            "folder": null,
            "protocolProfileBehavior": {
                "disableBodyPruning": true
            },
            "responses": [
                {
                    "id": "6aa33c342b5ec0dd66fd130d96c95bee",
                    "name": "Default",
                    "status": "200",
                    "mime": null,
                    "language": null,
                    "text": "\"{\n    \"priceRange\": \"String Content\",\n    \"branchOf\": {},\n    \"paymentAccepted\": \"String Content\",\n    \"openingHours\": \"String Content\",\n    \"currenciesAccepted\": \"String Content\"\n}\"",
                    "responseCode": {
                        "code": 200,
                        "name": ""
                    },
                    "requestObject": {
                        "url": "{{url}}\/Moving-Company\/",
                        "method": "GET",
                        "data": "",
                        "dataMode": "raw",
                        "protocolProfileBehavior": []
                    },
                    "headers": null,
                    "cookies": null,
                    "request": "be25f4d37643be827a407d83800924ec",
                    "collection": "a014bbfde60448503226075a3dab6b08"
                }
            ],
            "currentHelper": null,
            "helperAttributes": null,
            "collectionId": "a014bbfde60448503226075a3dab6b08",
            "rawModeData": ""
        }
    ]
}