{
    "id": "fc4e9a876e37810c6e1902b5ee9906b2",
    "name": "Music Album Production Type",
    "description": "Autogeneration of Music Album Production Type Schema.org object.",
    "auth": null,
    "events": null,
    "variables": [],
    "order": [],
    "folders_order": [],
    "folders": [],
    "requests": [
        {
            "id": "c85a89e39ed4ea219ef7b0fb4dd873ec",
            "name": "\/Music-Album-Production-Type\/",
            "url": "{{url}}\/Music-Album-Production-Type\/",
            "description": "Autogeneration of Music Album Production Type Schema.org object.",
            "data": [],
            "dataMode": "raw",
            "headerData": null,
            "method": "GET",
            "pathVariableData": null,
            "queryParams": null,
            "auth": null,
            "events": null,
            "folder": null,
            "protocolProfileBehavior": {
                "disableBodyPruning": true
            },
            "responses": [
                {
                    "id": "c85a89e39ed4ea219ef7b0fb4dd873ec",
                    "name": "Default",
                    "status": "200",
                    "mime": null,
                    "language": null,
                    "text": "\"[]\"",
                    "responseCode": {
                        "code": 200,
                        "name": ""
                    },
                    "requestObject": {
                        "url": "{{url}}\/Music-Album-Production-Type\/",
                        "method": "GET",
                        "data": "",
                        "dataMode": "raw",
                        "protocolProfileBehavior": []
                    },
                    "headers": null,
                    "cookies": null,
                    "request": "74329f86f3a3dd6dc5a1ef100b2a03de",
                    "collection": "fc4e9a876e37810c6e1902b5ee9906b2"
                }
            ],
            "currentHelper": null,
            "helperAttributes": null,
            "collectionId": "fc4e9a876e37810c6e1902b5ee9906b2",
            "rawModeData": ""
        }
    ]
}