{
    "id": "4c51433889eb94d5cb8cb7cbdc8a45dc",
    "name": "Place Of Worship",
    "description": "Autogeneration of Place Of Worship Schema.org object.",
    "auth": null,
    "events": null,
    "variables": [],
    "order": [],
    "folders_order": [],
    "folders": [],
    "requests": [
        {
            "id": "a20fcdf37746ff17a10e53b9ac621eb0",
            "name": "\/Place-Of-Worship\/",
            "url": "{{url}}\/Place-Of-Worship\/",
            "description": "Autogeneration of Place Of Worship Schema.org object.",
            "data": [],
            "dataMode": "raw",
            "headerData": null,
            "method": "GET",
            "pathVariableData": null,
            "queryParams": null,
            "auth": null,
            "events": null,
            "folder": null,
            "protocolProfileBehavior": {
                "disableBodyPruning": true
            },
            "responses": [
                {
                    "id": "a20fcdf37746ff17a10e53b9ac621eb0",
                    "name": "Default",
                    "status": "200",
                    "mime": null,
                    "language": null,
                    "text": "\"{\n    \"openingHours\": \"String Content\"\n}\"",
                    "responseCode": {
                        "code": 200,
                        "name": ""
                    },
                    "requestObject": {
                        "url": "{{url}}\/Place-Of-Worship\/",
                        "method": "GET",
                        "data": "",
                        "dataMode": "raw",
                        "protocolProfileBehavior": []
                    },
                    "headers": null,
                    "cookies": null,
                    "request": "97f947a2fd2f869808a92f8dcbcf35ee",
                    "collection": "4c51433889eb94d5cb8cb7cbdc8a45dc"
                }
            ],
            "currentHelper": null,
            "helperAttributes": null,
            "collectionId": "4c51433889eb94d5cb8cb7cbdc8a45dc",
            "rawModeData": ""
        }
    ]
}