{
    "id": "8d96f0f1133f5717e4b931ef78253b58",
    "name": "Pond",
    "description": "Autogeneration of Pond Schema.org object.",
    "auth": null,
    "events": null,
    "variables": [],
    "order": [],
    "folders_order": [],
    "folders": [],
    "requests": [
        {
            "id": "84ad61f9036858780f58a680f9eec613",
            "name": "\/Pond\/",
            "url": "{{url}}\/Pond\/",
            "description": "Autogeneration of Pond Schema.org object.",
            "data": [],
            "dataMode": "raw",
            "headerData": null,
            "method": "GET",
            "pathVariableData": null,
            "queryParams": null,
            "auth": null,
            "events": null,
            "folder": null,
            "protocolProfileBehavior": {
                "disableBodyPruning": true
            },
            "responses": [
                {
                    "id": "84ad61f9036858780f58a680f9eec613",
                    "name": "Default",
                    "status": "200",
                    "mime": null,
                    "language": null,
                    "text": "\"[]\"",
                    "responseCode": {
                        "code": 200,
                        "name": ""
                    },
                    "requestObject": {
                        "url": "{{url}}\/Pond\/",
                        "method": "GET",
                        "data": "",
                        "dataMode": "raw",
                        "protocolProfileBehavior": []
                    },
                    "headers": null,
                    "cookies": null,
                    "request": "191f5f78545159ace9931d4bc4361781",
                    "collection": "8d96f0f1133f5717e4b931ef78253b58"
                }
            ],
            "currentHelper": null,
            "helperAttributes": null,
            "collectionId": "8d96f0f1133f5717e4b931ef78253b58",
            "rawModeData": ""
        }
    ]
}