{
    "id": "f67693535f3b9b0e8d79e1be75179287",
    "name": "Post Office",
    "description": "Autogeneration of Post Office Schema.org object.",
    "auth": null,
    "events": null,
    "variables": [],
    "order": [],
    "folders_order": [],
    "folders": [],
    "requests": [
        {
            "id": "4585f2c142490d6cbf8a9548dd4f364b",
            "name": "\/post-office\/",
            "url": "{{url}}\/post-office\/",
            "description": "Autogeneration of Post Office Schema.org object.",
            "data": [],
            "dataMode": "raw",
            "headerData": null,
            "method": "GET",
            "pathVariableData": null,
            "queryParams": null,
            "auth": null,
            "events": null,
            "folder": null,
            "protocolProfileBehavior": {
                "disableBodyPruning": true
            },
            "responses": [
                {
                    "id": "4585f2c142490d6cbf8a9548dd4f364b",
                    "name": "Default",
                    "status": "200",
                    "mime": null,
                    "language": null,
                    "text": "[]",
                    "responseCode": {
                        "code": 200,
                        "name": ""
                    },
                    "requestObject": {
                        "url": "{{url}}\/post-office\/",
                        "method": "GET",
                        "data": "",
                        "dataMode": "raw",
                        "protocolProfileBehavior": []
                    },
                    "headers": null,
                    "cookies": null,
                    "request": "ddcd17b663064a45a858ad56f2bbae78",
                    "collection": "f67693535f3b9b0e8d79e1be75179287"
                }
            ],
            "currentHelper": null,
            "helperAttributes": null,
            "collectionId": "f67693535f3b9b0e8d79e1be75179287",
            "rawModeData": ""
        }
    ]
}