{
    "id": "24884fb9a3600b873020d81c30d93e5a",
    "name": "Rent Action",
    "description": "Autogeneration of Rent Action Schema.org object.",
    "auth": null,
    "events": null,
    "variables": [],
    "order": [],
    "folders_order": [],
    "folders": [],
    "requests": [
        {
            "id": "13e01f1c7af394f5c5b0e3bd48706f7c",
            "name": "\/rent-action\/",
            "url": "{{url}}\/rent-action\/",
            "description": "Autogeneration of Rent Action Schema.org object.",
            "data": [],
            "dataMode": "raw",
            "headerData": null,
            "method": "GET",
            "pathVariableData": null,
            "queryParams": null,
            "auth": null,
            "events": null,
            "folder": null,
            "protocolProfileBehavior": {
                "disableBodyPruning": true
            },
            "responses": [
                {
                    "id": "13e01f1c7af394f5c5b0e3bd48706f7c",
                    "name": "Default",
                    "status": "200",
                    "mime": null,
                    "language": null,
                    "text": "{\n    \"landlord\": {},\n    \"realEstateAgent\": {},\n    \"priceSpecification\": {},\n    \"price\": \"String Content\",\n    \"result\": {},\n    \"actionStatus\": {},\n    \"target\": {},\n    \"agent\": {},\n    \"startTime\": \"String Content\",\n    \"endTime\": \"String Content\",\n    \"instrument\": {},\n    \"participant\": {},\n    \"object\": {},\n    \"error\": {},\n    \"location\": {},\n    \"sameAs\": {},\n    \"url\": {},\n    \"image\": {},\n    \"additionalType\": {},\n    \"name\": \"String Content\",\n    \"identifier\": {},\n    \"potentialAction\": {},\n    \"mainEntityOfPage\": {},\n    \"description\": \"String Content\",\n    \"disambiguatingDescription\": \"String Content\",\n    \"alternateName\": \"String Content\"\n}",
                    "responseCode": {
                        "code": 200,
                        "name": ""
                    },
                    "requestObject": {
                        "url": "{{url}}\/rent-action\/",
                        "method": "GET",
                        "data": "",
                        "dataMode": "raw",
                        "protocolProfileBehavior": []
                    },
                    "headers": null,
                    "cookies": null,
                    "request": "595b1c076f5bac9e39fa0a2f8058db98",
                    "collection": "24884fb9a3600b873020d81c30d93e5a"
                }
            ],
            "currentHelper": null,
            "helperAttributes": null,
            "collectionId": "24884fb9a3600b873020d81c30d93e5a",
            "rawModeData": ""
        }
    ]
}