{
    "id": "8a9d097a6a493cdab34d2866de51466d",
    "name": "Tie Action",
    "description": "Autogeneration of Tie Action Schema.org object.",
    "auth": null,
    "events": null,
    "variables": [],
    "order": [],
    "folders_order": [],
    "folders": [],
    "requests": [
        {
            "id": "502cd5616344e8ab15a6e1ecd4b8db79",
            "name": "\/tie-action\/",
            "url": "{{url}}\/tie-action\/",
            "description": "Autogeneration of Tie Action Schema.org object.",
            "data": [],
            "dataMode": "raw",
            "headerData": null,
            "method": "GET",
            "pathVariableData": null,
            "queryParams": null,
            "auth": null,
            "events": null,
            "folder": null,
            "protocolProfileBehavior": {
                "disableBodyPruning": true
            },
            "responses": [
                {
                    "id": "502cd5616344e8ab15a6e1ecd4b8db79",
                    "name": "Default",
                    "status": "200",
                    "mime": null,
                    "language": null,
                    "text": "{\n    \"result\": {},\n    \"actionStatus\": {},\n    \"target\": {},\n    \"agent\": {},\n    \"startTime\": \"String Content\",\n    \"endTime\": \"String Content\",\n    \"instrument\": {},\n    \"participant\": {},\n    \"object\": {},\n    \"error\": {},\n    \"location\": {},\n    \"sameAs\": {},\n    \"url\": {},\n    \"image\": {},\n    \"additionalType\": {},\n    \"name\": \"String Content\",\n    \"identifier\": {},\n    \"potentialAction\": {},\n    \"mainEntityOfPage\": {},\n    \"description\": \"String Content\",\n    \"disambiguatingDescription\": \"String Content\",\n    \"alternateName\": \"String Content\"\n}",
                    "responseCode": {
                        "code": 200,
                        "name": ""
                    },
                    "requestObject": {
                        "url": "{{url}}\/tie-action\/",
                        "method": "GET",
                        "data": "",
                        "dataMode": "raw",
                        "protocolProfileBehavior": []
                    },
                    "headers": null,
                    "cookies": null,
                    "request": "ae5d2fca6d4484d2d2f764589c33c857",
                    "collection": "8a9d097a6a493cdab34d2866de51466d"
                }
            ],
            "currentHelper": null,
            "helperAttributes": null,
            "collectionId": "8a9d097a6a493cdab34d2866de51466d",
            "rawModeData": ""
        }
    ]
}