{
    "id": "1b9fce1160765e9163dc9202a618adb4",
    "name": "T V Clip",
    "description": "Autogeneration of T V Clip Schema.org object.",
    "auth": null,
    "events": null,
    "variables": [],
    "order": [],
    "folders_order": [],
    "folders": [],
    "requests": [
        {
            "id": "789f76b081dc44030803c26bdfa32a8a",
            "name": "\/T-V-Clip\/",
            "url": "{{url}}\/T-V-Clip\/",
            "description": "Autogeneration of T V Clip Schema.org object.",
            "data": [],
            "dataMode": "raw",
            "headerData": null,
            "method": "GET",
            "pathVariableData": null,
            "queryParams": null,
            "auth": null,
            "events": null,
            "folder": null,
            "protocolProfileBehavior": {
                "disableBodyPruning": true
            },
            "responses": [
                {
                    "id": "789f76b081dc44030803c26bdfa32a8a",
                    "name": "Default",
                    "status": "200",
                    "mime": null,
                    "language": null,
                    "text": "{\n    \"partOfTVSeries\": {},\n    \"actor\": {},\n    \"partOfSeries\": {},\n    \"partOfEpisode\": {},\n    \"partOfSeason\": {},\n    \"musicBy\": {},\n    \"directors\": {},\n    \"director\": {},\n    \"actors\": {},\n    \"clipNumber\": \"String Content\"\n}",
                    "responseCode": {
                        "code": 200,
                        "name": ""
                    },
                    "requestObject": {
                        "url": "{{url}}\/T-V-Clip\/",
                        "method": "GET",
                        "data": "",
                        "dataMode": "raw",
                        "protocolProfileBehavior": []
                    },
                    "headers": null,
                    "cookies": null,
                    "request": "74d79dd0616ee3492a5bf18f142d3dda",
                    "collection": "1b9fce1160765e9163dc9202a618adb4"
                }
            ],
            "currentHelper": null,
            "helperAttributes": null,
            "collectionId": "1b9fce1160765e9163dc9202a618adb4",
            "rawModeData": ""
        }
    ]
}