{
    "id": "c95d8c5c85baa8d5242347e16e7daa58",
    "name": "College Or University",
    "description": "Autogeneration of College Or University Schema.org object.",
    "auth": null,
    "events": null,
    "variables": [],
    "order": [],
    "folders_order": [],
    "folders": [],
    "requests": [
        {
            "id": "b0195b05547f380625b4e47229445c0d",
            "name": "\/College-Or-University\/",
            "url": "{{url}}\/College-Or-University\/",
            "description": "Autogeneration of College Or University Schema.org object.",
            "data": [],
            "dataMode": "raw",
            "headerData": null,
            "method": "GET",
            "pathVariableData": null,
            "queryParams": null,
            "auth": null,
            "events": null,
            "folder": null,
            "protocolProfileBehavior": {
                "disableBodyPruning": true
            },
            "responses": [
                {
                    "id": "b0195b05547f380625b4e47229445c0d",
                    "name": "Default",
                    "status": "200",
                    "mime": null,
                    "language": null,
                    "text": "\"{\n    \"alumni\": {},\n    \"serviceArea\": {},\n    \"funder\": {},\n    \"areaServed\": {},\n    \"memberOf\": {},\n    \"events\": {},\n    \"subOrganization\": {},\n    \"hasOfferCatalog\": {},\n    \"globalLocationNumber\": \"String Content\",\n    \"reviews\": {},\n    \"members\": {},\n    \"aggregateRating\": {},\n    \"duns\": \"String Content\",\n    \"taxID\": \"String Content\",\n    \"award\": \"String Content\",\n    \"makesOffer\": {},\n    \"contactPoints\": {},\n    \"awards\": \"String Content\",\n    \"seeks\": {},\n    \"member\": {},\n    \"founders\": {},\n    \"dissolutionDate\": \"String Content\",\n    \"address\": {},\n    \"logo\": {},\n    \"employees\": {},\n    \"telephone\": \"String Content\",\n    \"email\": \"String Content\",\n    \"department\": {},\n    \"contactPoint\": {},\n    \"parentOrganization\": {},\n    \"legalName\": \"String Content\",\n    \"foundingDate\": \"String Content\",\n    \"employee\": {},\n    \"numberOfEmployees\": {},\n    \"naics\": \"String Content\",\n    \"hasPOS\": {},\n    \"review\": {},\n    \"foundingLocation\": {},\n    \"owns\": {},\n    \"event\": {},\n    \"founder\": {},\n    \"publishingPrinciples\": {},\n    \"sponsor\": {},\n    \"isicV4\": \"String Content\",\n    \"location\": {},\n    \"brand\": {},\n    \"vatID\": \"String Content\",\n    \"leiCode\": \"String Content\",\n    \"faxNumber\": \"String Content\",\n    \"sameAs\": {},\n    \"url\": {},\n    \"image\": {},\n    \"additionalType\": {},\n    \"name\": \"String Content\",\n    \"identifier\": {},\n    \"potentialAction\": {},\n    \"mainEntityOfPage\": {},\n    \"description\": \"String Content\",\n    \"disambiguatingDescription\": \"String Content\",\n    \"alternateName\": \"String Content\"\n}\"",
                    "responseCode": {
                        "code": 200,
                        "name": ""
                    },
                    "requestObject": {
                        "url": "{{url}}\/College-Or-University\/",
                        "method": "GET",
                        "data": "",
                        "dataMode": "raw",
                        "protocolProfileBehavior": []
                    },
                    "headers": null,
                    "cookies": null,
                    "request": "2cef018e14615c56bccf09e9c4212003",
                    "collection": "c95d8c5c85baa8d5242347e16e7daa58"
                }
            ],
            "currentHelper": null,
            "helperAttributes": null,
            "collectionId": "c95d8c5c85baa8d5242347e16e7daa58",
            "rawModeData": ""
        }
    ]
}