{
    "id": "41f8cd9291af57545a0d830c12169f2f",
    "name": "Compound Price Specification",
    "description": "Autogeneration of Compound Price Specification Schema.org object.",
    "auth": null,
    "events": null,
    "variables": [],
    "order": [],
    "folders_order": [],
    "folders": [],
    "requests": [
        {
            "id": "0d52257bed6764f193e5caf8257b21af",
            "name": "\/Compound-Price-Specification\/",
            "url": "{{url}}\/Compound-Price-Specification\/",
            "description": "Autogeneration of Compound Price Specification Schema.org object.",
            "data": [],
            "dataMode": "raw",
            "headerData": null,
            "method": "GET",
            "pathVariableData": null,
            "queryParams": null,
            "auth": null,
            "events": null,
            "folder": null,
            "protocolProfileBehavior": {
                "disableBodyPruning": true
            },
            "responses": [
                {
                    "id": "0d52257bed6764f193e5caf8257b21af",
                    "name": "Default",
                    "status": "200",
                    "mime": null,
                    "language": null,
                    "text": "\"{\n    \"priceComponent\": {},\n    \"minPrice\": 10,\n    \"eligibleTransactionVolume\": {},\n    \"maxPrice\": 10,\n    \"priceCurrency\": \"String Content\",\n    \"eligibleQuantity\": {},\n    \"validFrom\": \"String Content\",\n    \"validThrough\": \"String Content\",\n    \"price\": \"String Content\",\n    \"valueAddedTaxIncluded\": 1\n}\"",
                    "responseCode": {
                        "code": 200,
                        "name": ""
                    },
                    "requestObject": {
                        "url": "{{url}}\/Compound-Price-Specification\/",
                        "method": "GET",
                        "data": "",
                        "dataMode": "raw",
                        "protocolProfileBehavior": []
                    },
                    "headers": null,
                    "cookies": null,
                    "request": "d3c41e3057309981dfac35761c9487c1",
                    "collection": "41f8cd9291af57545a0d830c12169f2f"
                }
            ],
            "currentHelper": null,
            "helperAttributes": null,
            "collectionId": "41f8cd9291af57545a0d830c12169f2f",
            "rawModeData": ""
        }
    ]
}