{
    "id": "3111d23a06c13d380c329d46d6de835c",
    "name": "Hindu Temple",
    "description": "Autogeneration of Hindu Temple Schema.org object.",
    "auth": null,
    "events": null,
    "variables": [],
    "order": [],
    "folders_order": [],
    "folders": [],
    "requests": [
        {
            "id": "a80da1e32d72ca0a856d78710fe469ad",
            "name": "\/Hindu-Temple\/",
            "url": "{{url}}\/Hindu-Temple\/",
            "description": "Autogeneration of Hindu Temple Schema.org object.",
            "data": [],
            "dataMode": "raw",
            "headerData": null,
            "method": "GET",
            "pathVariableData": null,
            "queryParams": null,
            "auth": null,
            "events": null,
            "folder": null,
            "protocolProfileBehavior": {
                "disableBodyPruning": true
            },
            "responses": [
                {
                    "id": "a80da1e32d72ca0a856d78710fe469ad",
                    "name": "Default",
                    "status": "200",
                    "mime": null,
                    "language": null,
                    "text": "\"[]\"",
                    "responseCode": {
                        "code": 200,
                        "name": ""
                    },
                    "requestObject": {
                        "url": "{{url}}\/Hindu-Temple\/",
                        "method": "GET",
                        "data": "",
                        "dataMode": "raw",
                        "protocolProfileBehavior": []
                    },
                    "headers": null,
                    "cookies": null,
                    "request": "1c3ab1162ef6be7e05206f658618ede3",
                    "collection": "3111d23a06c13d380c329d46d6de835c"
                }
            ],
            "currentHelper": null,
            "helperAttributes": null,
            "collectionId": "3111d23a06c13d380c329d46d6de835c",
            "rawModeData": ""
        }
    ]
}