{
    "id": "6139554457b3f8e9d7a20451c20aa002",
    "name": "Zoo",
    "description": "Autogeneration of Zoo Schema.org object.",
    "auth": null,
    "events": null,
    "variables": [],
    "order": [],
    "folders_order": [],
    "folders": [],
    "requests": [
        {
            "id": "a2d0a04f2a602d20154d292e4fcedbdd",
            "name": "\/Zoo\/",
            "url": "{{url}}\/Zoo\/",
            "description": "Autogeneration of Zoo Schema.org object.",
            "data": [],
            "dataMode": "raw",
            "headerData": null,
            "method": "GET",
            "pathVariableData": null,
            "queryParams": null,
            "auth": null,
            "events": null,
            "folder": null,
            "protocolProfileBehavior": {
                "disableBodyPruning": true
            },
            "responses": [
                {
                    "id": "a2d0a04f2a602d20154d292e4fcedbdd",
                    "name": "Default",
                    "status": "200",
                    "mime": null,
                    "language": null,
                    "text": "\"{\n    \"openingHours\": \"String Content\"\n}\"",
                    "responseCode": {
                        "code": 200,
                        "name": ""
                    },
                    "requestObject": {
                        "url": "{{url}}\/Zoo\/",
                        "method": "GET",
                        "data": "",
                        "dataMode": "raw",
                        "protocolProfileBehavior": []
                    },
                    "headers": null,
                    "cookies": null,
                    "request": "b453155f1f074419864923bc3baa0591",
                    "collection": "6139554457b3f8e9d7a20451c20aa002"
                }
            ],
            "currentHelper": null,
            "helperAttributes": null,
            "collectionId": "6139554457b3f8e9d7a20451c20aa002",
            "rawModeData": ""
        }
    ]
}